{"Smite": 3, "RandomActsOfGaming": 8, "Fitness": 3, "teenagers": 2, "randomactsofamazon": 1, "friendsafari": 17, "ShinyPokemon": 2, "politics": 3, "BorderlandsPreSequel": 6, "pokemon": 24, "fantasyfootball": 6, "GlobalOffensive": 3, "NBA2k": 1, "CasualPokemonTrades": 638, "GameTrade": 4, "SVExchange": 15, "GlobalOffensiveTrade": 3, "PKMNRedditLeague": 6, "gaming": 1, "GiftofGames": 4, "gifs": 3, "askscience": 3, "PokePlazaReferences": 16, "trees": 6, "relaxedpokemontrades": 2, "Gaming4Gamers": 1, "pokemontrades": 3, "Pokemongiveaway": 43, "projectzomboid": 8, "Megaten": 4, "AskReddit": 27, "PokemonPlaza": 115, "Music": 3}