{"PanicHistory": 1, "Poetry": 1, "london": 1, "EliteDangerous": 3, "carporn": 3, "blender": 4, "GlobalOffensive": 16, "Showerthoughts": 3, "whowouldwin": 6, "GrandTheftAutoV": 7, "WTF": 6, "MilitaryPorn": 2, "food": 1, "trees": 10, "Jokes": 1, "AbusePorn2": 1, "Steam": 9, "gifs": 1, "creepyPMs": 1, "Pegging": 3, "Celebs": 1, "subaru": 1, "AdviceAnimals": 1, "montageparodies": 4, "Hatfilms": 5, "ShitRedditSays": 3, "ebola": 4, "AskLiteraryStudies": 3, "dayzrp": 1, "mildlyinteresting": 2, "pcgaming": 1, "badhistory": 1, "gentlemanboners": 2, "xboxone": 1, "see": 1, "PS3": 1, "4x4": 2, "TheFutureIsNow": 1, "DunderMifflin": 1, "lotr": 2, "knifeparty": 1, "microbiology": 1, "DrunkOrAKid": 2, "Nexus5": 8, "leagueoflegends": 21, "worldnews": 14, "pcmasterrace": 12, "europe": 4, "CivStrategy": 1, "battlefield3": 7, "AskReddit": 78, "news": 7, "WritingPrompts": 1, "dayz": 471, "Borderlands": 1, "pics": 5, "nosleep": 4, "badBIOS": 2, "battlestations": 2, "gamingpc": 1, "todayilearned": 2, "conspiratard": 1, "Music": 1, "BorderlandsPreSequel": 2, "FiftyFifty": 1, "AskHistorians": 3, "spam": 1, "retrobattlestations": 1, "battlefield_4": 3, "explainlikeimfive": 5, "arma": 4, "CombatFootage": 4, "bapcsalesuk": 1, "Unexpected": 2, "Suomi": 1, "RedditArmie": 1, "bmx": 9, "TiADiscussion": 1, "television": 2, "rage": 2, "science": 1, "starcitizen": 6, "civ": 3, "KerbalSpaceProgram": 2, "MMA": 12, "videos": 1, "boston": 1, "theydidthemath": 3, "h1z1": 6, "onions": 3, "funny": 17, "technology": 2, "IAmA": 3, "EAF": 1, "pokemonconspiracies": 2, "saplings": 4, "VPN": 1, "TheFence": 1, "gaming": 9, "aww": 2, "Futurology": 1, "Games": 6, "playrust": 14, "CampingandHiking": 1, "GirlGamers": 1, "TumblrInAction": 1, "ImGoingToHellForThis": 2}