{"LifeProTips": 4, "pettyrevenge": 2, "cringepics": 1, "sju": 1, "nottingham": 54, "woodworking": 1, "everymanshouldknow": 2, "dataisbeautiful": 8, "stalker": 6, "ass": 1, "geography": 1, "Showerthoughts": 4, "blog": 1, "WTF": 7, "ImaginaryMonsters": 1, "JRITSlounge": 2, "Judaism": 2, "gonewild": 1, "food": 1, "UpliftingNews": 1, "Netrunner": 6, "ebola": 35, "Fitness": 1, "cogsci": 1, "thewalkingdead": 4, "homestead": 2, "gifs": 6, "AbandonedPorn": 2, "badeconomics": 2, "nfl": 9, "4chan": 2, "AdviceAnimals": 12, "Cyberpunk": 5, "Libertarian": 3, "starcitizen": 4, "StarWars": 1, "PlayItAgainSam": 1, "GermanPractice": 1, "whatisthisthing": 1, "gaming": 5, "TheSimpsons": 3, "civbeyondearth": 2, "interestingasfuck": 1, "books": 4, "changemyview": 1, "TwoXChromosomes": 6, "twitchplayspokemon": 1, "Android": 1, "AnarchistNews": 1, "Berserk": 1, "fantasyfootball": 6, "psychology": 1, "space": 2, "wow": 1, "AskReddit": 48, "mindcrack": 1, "BMW": 6, "worldnews": 50, "lifehacks": 3, "TheLastAirbender": 1, "guns": 1, "europe": 1, "trashy": 1, "cars": 7, "Economics": 15, "Drama": 1, "Cynicalbrit": 1, "archeage": 30, "vinyl": 1, "news": 34, "minipainting": 4, "ClimbingPorn": 1, "Unexpected": 1, "InternetIsBeautiful": 1, "bravefrontier": 1, "OnePiece": 10, "merecraft": 6, "personalfinance": 8, "creepy": 1, "pics": 11, "49ers": 1, "ukpolitics": 1, "Tinder": 1, "Gunpla": 1, "cambridge": 1, "TrueReddit": 2, "todayilearned": 5, "mildlyinteresting": 2, "gorillaz": 2, "conspiratard": 6, "Health": 1, "Documentaries": 3, "TrollXChromosomes": 2, "DOS": 1, "unitedkingdom": 2, "environment": 2, "OldSchoolCool": 2, "Minecraft": 2, "Nikon": 2, "Seattle": 6, "HomeImprovement": 1, "explainlikeimfive": 13, "CombatFootage": 2, "TrollYChromosome": 4, "climate": 2, "MapPorn": 1, "AskMen": 2, "EDC": 2, "television": 3, "Colorado": 10, "worldpolitics": 1, "science": 6, "offbeat": 1, "movies": 11, "MarkMyWords": 1, "DotA2": 19, "austrian_economics": 3, "RealEstate": 1, "history": 1, "fullmoviesonyoutube": 1, "NeoFAG": 5, "videos": 22, "gadgets": 6, "relationship_advice": 2, "politics": 8, "galaxynote4": 2, "technology": 5, "Cinemagraphs": 1, "SRSsucks": 7, "funny": 23, "AskUK": 1, "24hoursupport": 1, "DestinyTheGame": 6, "AskSocialScience": 4, "Watercolor": 3, "talesfromtechsupport": 1, "popping": 1, "nottheonion": 10, "BasicIncome": 6, "lectures": 1, "Banished": 1, "askscience": 2, "Futurology": 178, "philosophy": 14, "budgetfood": 5, "Driveclub": 1, "betakeys": 1, "Games": 16, "playrust": 7, "climbing": 8, "Physics": 2, "disagreeable": 4, "tressless": 1, "samsung": 2, "chicago": 3, "CFB": 5, "fsm": 1, "atheism": 3, "nasa": 1, "trains": 9, "chemistry": 1, "gainit": 1}