{"RapeSquadKillas": 1, "Boxing": 19, "nsfw": 1, "dataisbeautiful": 4, "oliviawilde": 1, "Fitness": 7, "woodycraft": 1, "GlobalOffensive": 1, "minnesotavikings": 4, "writing": 3, "2007scape": 23, "WTF": 3, "piano": 3, "soccer": 8, "PublicFreakout": 1, "buildapcsales": 1, "smashbros": 1, "cringepics": 2, "belgium": 1, "beards": 2, "thewalkingdead": 1, "gifs": 1, "motorcycles": 1, "Celebs": 1, "nfl": 2, "Watches": 2, "WeAreTheMusicMakers": 1, "AdviceAnimals": 4, "montageparodies": 1, "cringe": 1, "SoundersFC": 4, "mildlyinteresting": 2, "Radioresepsjonen": 2, "AskWomen": 7, "totalwar": 2, "opieandanthony": 15, "Chargers": 6, "Naruto": 2, "pebble": 1, "fantasyfootball": 10, "cosplay": 1, "wow": 2, "AskReddit": 49, "DarkNetMarkets": 4, "breakingbad": 1, "malefashionadvice": 2, "PKA": 431, "leagueoflegends": 4, "modnews": 1, "worldnews": 5, "MonsterHunter": 3, "pcmasterrace": 1, "chillstep": 1, "cars": 1, "Frugal": 1, "baseball": 7, "dayz": 4, "CasualConversation": 10, "pics": 16, "WWE": 1, "49ers": 2, "progmetal": 2, "anime": 4, "redorchestra": 3, "gamingpc": 1, "apple": 1, "Firearms": 2, "tifu": 3, "SquaredCircle": 4, "stopsmoking": 3, "TheRealmOfMianite": 2, "explainlikeimfive": 10, "arma": 2, "CombatFootage": 10, "fatpeoplehate": 13, "hiphopheads": 2, "nrl": 4, "oddlysatisfying": 5, "asoiaf": 9, "PKAGaming": 1, "Random_acts_of_CCG": 1, "pathofexile": 23, "civ": 1, "kindle": 1, "videos": 8, "COents": 1, "learnprogramming": 5, "webdev": 1, "supremeclothing": 22, "ripcity": 3, "technology": 3, "nba": 2, "funny": 2, "chelseafc": 9, "Seahawks": 7, "OpTicGaming": 1, "talesfromtechsupport": 3, "gaming": 20, "ASRoma": 1, "MLS": 4, "CFB": 1, "atheism": 17, "vfx": 2, "Accounting": 2}