{"pettyrevenge": 1, "golf": 8, "StarWarsEU": 1, "friskydingo": 1, "adventuretime": 1, "fantasyfootball": 12, "TheBrewery": 2, "masseffect": 8, "BuyItForLife": 2, "london": 2, "wiiu": 1, "RandomActsOfGaming": 7, "shield": 1, "Dallas": 10, "startrek": 6, "harrypotter": 13, "fallout3": 1, "2007scape": 1, "thewalkingdead": 2, "WTF": 1, "Minecraft360": 1, "offmychest": 2, "smallbusiness": 2, "photoshopbattles": 2, "food": 4, "photography": 1, "trees": 4, "Fitness": 11, "pcmasterrace": 7, "halo": 2, "gifs": 2, "Art": 1, "enlightenedbirdmen": 2, "DiamondClub": 2, "orlando": 1, "woahdude": 1, "Watches": 5, "4chan": 1, "oblivion": 1, "SubredditDrama": 1, "Cyberpunk": 1, "SwagBucks": 8, "psych": 1, "Seattle": 3, "SithOrder": 2, "StarWars": 280, "mildlyinteresting": 3, "nfl": 4, "incremental_games": 5, "watercooling": 1, "TheSimpsons": 11, "MST3K": 1, "swgemu": 4, "books": 2, "changemyview": 6, "roosterteeth": 2, "MetaHolo": 4, "PS4": 3, "gameofthrones": 3, "space": 1, "3Dprinting": 1, "AskReddit": 56, "MechanicalKeyboards": 1, "AdviceAnimals": 25, "worldnews": 5, "memes": 1, "TheLastAirbender": 1, "DarkSouls2": 1, "SCP": 2, "math": 1, "MawInstallation": 1, "badMovies": 1, "wisconsin": 3, "cars": 2, "Economics": 2, "Metal": 4, "dune": 3, "news": 1, "doctorwho": 2, "htpc": 1, "dragoncon": 2, "Toughmudder": 2, "WritingPrompts": 3, "calvinandhobbes": 1, "personalfinance": 4, "AmateurRoomPorn": 2, "pics": 11, "49ers": 1, "Modesto": 1, "RX8": 1, "bestof": 2, "AskPhysics": 2, "battlestations": 4, "buildapc": 5, "apple": 4, "Yogscast": 4, "todayilearned": 11, "Delaware": 3, "reactiongifs": 5, "KingOfTheHill": 1, "ucf": 1, "subaru": 4, "Music": 3, "Showerthoughts": 16, "pokemon": 1, "tf2": 2, "DnD": 1, "circlejerk": 8, "COPYRIGHT": 1, "lego": 5, "Physics": 2, "SquaredCircle": 1, "TheWire": 1, "applehelp": 2, "consoledeals": 2, "iphone": 2, "Zune": 1, "GrandTheftAutoV": 2, "eyes": 1, "footwork": 1, "Fallout": 1, "swtor": 23, "batman": 2, "gamegrumps": 6, "CallOfDuty": 1, "marvelstudios": 1, "oddlysatisfying": 2, "3DSdeals": 1, "rule34": 1, "LifeProTips": 3, "skyrim": 8, "starcitizen": 3, "redditstealthCOC": 1, "Marvel": 2, "TheHolocronArchives": 5, "beermoney": 2, "worldpolitics": 9, "VictoriaBC": 1, "Justrolledintotheshop": 8, "movies": 12, "rutgers": 4, "knives": 1, "Cleveland": 1, "KerbalSpaceProgram": 3, "captionthis": 1, "homelab": 1, "AskScienceFiction": 3, "videos": 3, "MilitaryPorn": 2, "KotakuInAction": 6, "gadgets": 6, "gamecollecting": 1, "DIY": 4, "tiltshift": 1, "redsox": 1, "FilthyFrank": 2, "ClashOfClans": 9, "technology": 3, "funny": 17, "techsupportmacgyver": 1, "bicycling": 1, "travel": 2, "pitbulls": 2, "IAmA": 4, "scifi": 6, "Gundam": 10, "gaming": 19, "Omaha": 1, "aww": 2, "Trove": 8, "running": 3, "castmeas": 3, "Games": 2, "FixedGearBicycle": 1, "nintendo": 1, "Minecraft": 4, "fasting": 1, "dataisbeautiful": 3, "newjersey": 2, "TimAndEric": 1, "atheism": 1, "Fantasy": 1, "TumblrInAction": 14, "titanfall": 8, "Sithit": 19}