{"inthenews": 2, "BuyItForLife": 2, "woodworking": 7, "tesdcares": 1, "Showerthoughts": 1, "blog": 2, "Connecticut": 3, "Diablo": 5, "WTF": 3, "linuxquestions": 26, "Jeep": 1, "Steam": 2, "exchangeserver": 4, "gifs": 3, "Cisco": 2, "motorcycles": 6, "nfl": 12, "woahdude": 1, "AdviceAnimals": 9, "penguins": 6, "Libertarian": 4, "CasualConversation": 2, "Paleo": 3, "TheSimpsons": 1, "Denver": 4, "vmware": 8, "heroesofthestorm": 2, "AskReddit": 45, "malefashionadvice": 1, "leagueoflegends": 7, "worldnews": 8, "pcmasterrace": 2, "magicTCG": 6, "math": 1, "europe": 1, "bestof": 5, "cars": 7, "CrazyIdeas": 1, "Flyers": 2, "news": 10, "florida": 1, "tampajobs": 6, "pics": 12, "Planetside": 1, "wheredidthesodago": 2, "buildapc": 3, "apple": 4, "todayilearned": 19, "ServerPorn": 1, "AmIFreeToGo": 9, "reactiongifs": 2, "TrollXChromosomes": 1, "tifu": 1, "findfashion": 1, "computertechs": 1, "networking": 29, "Bad_Cop_No_Donut": 1, "Homebrewing": 2, "sports": 2, "eagles": 2, "battlefield_4": 1, "explainlikeimfive": 4, "hockey": 10, "cablefail": 1, "tasker": 5, "pittsburgh": 18, "Eve": 4, "roguelikes": 1, "LifeProTips": 1, "thinkpad": 1, "tampa": 2, "slavelabour": 1, "toronto": 12, "sysadmin": 468, "television": 1, "minerapocalypse": 1, "techsupportgore": 11, "science": 1, "offbeat": 1, "videos": 1, "rit": 1, "hardware": 1, "engineering": 1, "Netherlands": 1, "leafs": 8, "technology": 17, "funny": 22, "food": 3, "nottheonion": 5, "talesfromtechsupport": 15, "gaming": 3, "killthosewhodisagree": 2, "mac": 1, "Games": 8, "windows": 2, "CFB": 13, "gadgets": 4, "TumblrInAction": 6, "cableporn": 1}